src/__init__.py
src/cli.py
src/app/__init__.py
src/app/commands.py
src/app/utils.py
src/idf/__init__.py
src/idf/commands.py
src/idf/utils.py
src/utils/__init__.py
src/utils/config.py
src/utils/constants.py
src/utils/general.py
espy_cli-1.0.0.dist-info/LICENSE
espy_cli-1.0.0.dist-info/METADATA
espy_cli-1.0.0.dist-info/WHEEL
espy_cli-1.0.0.dist-info/entry_points.txt
espy_cli-1.0.0.dist-info/top_level.txt
espy_cli-1.0.0.dist-info/RECORD
