Metadata-Version: 2.1
Name: espy-cli
Version: 1.0.0
Summary: A Command Line application to manage your ESP-IDF projects with ease.
Home-page: https://github.com/13point5/espy-cli
Author: Bharath Sriraam R R
Author-email: albharath.1305@gmail.com
License: UNKNOWN
Platform: UNKNOWN
Classifier: Programming Language :: Python :: 3
Classifier: License :: OSI Approved :: MIT License
Classifier: Operating System :: POSIX :: Linux
Requires-Dist: appdirs (==1.4.3)
Requires-Dist: click (==7.0)
Requires-Dist: terminaltables (==3.1.0)
